src/fulladder.v
module fulladder (
    input wire a,
    input wire b,
    input wire cin,
    output wire sum,
    output wire cout
);
    assign sum = a ^ b ^ cin; 
    assign cout = (a & b) | (cin & (a ^ b)); 
endmodule

testbench/fulladder_tb.v
`timescale 1ns/1ps

module fulladder_tb;

    // Inputs
    reg a, b, cin;

    // Outputs
    wire sum, cout;

    // Instantiate the DUT
    fulladder uut (
        .a(a),
        .b(b),
        .cin(cin),
        .sum(sum),
        .cout(cout)
    );

    initial begin
        // Create VCD file
        $dumpfile("fulladder_tb.vcd");
        $dumpvars(0, fulladder_tb);

        // Print header
        $display("Time\t a b cin | sum cout");
        $monitor("%0t\t %b %b  %b  |  %b    %b",
                  $time, a, b, cin, sum, cout);

        // Initialize inputs at time 0
        a = 0;
        b = 0;
        cin = 0;

        #10;
        cin = 1;

        #10;
        b = 1;
        cin = 0;

        #10;
        cin = 1;

        #10;
        a = 1;
        b = 0;
        cin = 0;

        #10;
        cin = 1;

        #10;
        b = 1;
        cin = 0;

        #10;
        cin = 1;

        #10;
        $finish;
    end

endmodule

fulladder_tb.vcd
$date
	Mon Jun 29 10:53:36 2026
$end
$version
	Icarus Verilog
$end
$timescale
	1ps
$end
$scope module fulladder_tb $end
$var wire 1 ! sum $end
$var wire 1 " cout $end
$var reg 1 # a $end
$var reg 1 $ b $end
$var reg 1 % cin $end
$scope module uut $end
$var wire 1 # a $end
$var wire 1 $ b $end
$var wire 1 % cin $end
$var wire 1 " cout $end
$var wire 1 ! sum $end
$upscope $end
$upscope $end
$enddefinitions $end
$comment Show the parameter values. $end
$dumpall
$end
#0
$dumpvars
0%
0$
0#
0"
0!
$end
#10000
1!
1%
#20000
0%
1$
#30000
1"
0!
1%
#40000
0"
1!
0%
0$
1#
#50000
1"
0!
1%
#60000
0%
1$
#70000
1!
1%
